nonebot_plugin_autopush/__init__.py
nonebot_plugin_autopush/__main__.py
nonebot_plugin_autopush/config.py
nonebot_plugin_autopush/push.py
nonebot_plugin_autopush/servers.py
nonebot_plugin_autopush-0.1.1.dist-info/LICENSE
nonebot_plugin_autopush-0.1.1.dist-info/METADATA
nonebot_plugin_autopush-0.1.1.dist-info/WHEEL
nonebot_plugin_autopush-0.1.1.dist-info/top_level.txt
nonebot_plugin_autopush-0.1.1.dist-info/RECORD
