Metadata-Version: 2.1
Name: nonebot-plugin-autopush
Version: 0.1.1
Summary: NoneBot2 自动状态推送
Author-email: XiaoDeng3386 <1744793737@qq.com>
License: MIT
Requires-Python: >=3.9
License-File: LICENSE
Requires-Dist: nonebot2 >=2.2.0
Requires-Dist: httpx >=0.27.0
Requires-Dist: nonebot-plugin-apscheduler >=0.5.0
